{
  "_class": "shapePath",
  "booleanOperation": -1,
  "do_objectID": "F6E558B6-A1DC-49D8-BE9C-F75D8EFB4B0C",
  "edited": true,
  "exportOptions": {
    "_class": "exportOptions",
    "do_objectID": "2C27AF68-4667-4010-B01E-F86CDF1CFFC8",
    "exportFormats": [
    ],
    "includedLayerIds": [
    ],
    "layerOptions": 0,
    "shouldTrim": false
  },
  "frame": {
    "_class": "rect",
    "constrainProportions": false,
    "do_objectID": "96A6E584-DBA2-4B75-8E4A-DAF78AF41D49",
    "height": 10,
    "width": 10,
    "x": 2,
    "y": 2
  },
  "isClosed": true,
  "isFlippedHorizontal": false,
  "isFlippedVertical": false,
  "isLocked": false,
  "isVisible": true,
  "layerListExpandedType": 0,
  "name": "Path",
  "nameIsFixed": false,
  "path": {
    "_class": "path",
    "isClosed": true,
    "pointRadiusBehaviour": 0,
    "points": [
      {
        "_class": "curvePoint",
        "cornerRadius": 0,
        "curveFrom": "{0, 0.22385762510307947}",
        "curveMode": 2,
        "curveTo": "{0, 0.77614237489692084}",
        "hasCurveFrom": true,
        "hasCurveTo": true,
        "point": "{0, 0.5}"
      },
      {
        "_class": "curvePoint",
        "cornerRadius": 0,
        "curveFrom": "{0.77614237489692073, 0}",
        "curveMode": 2,
        "curveTo": "{0.22385762510307963, 0}",
        "hasCurveFrom": true,
        "hasCurveTo": true,
        "point": "{0.5, 0}"
      },
      {
        "_class": "curvePoint",
        "cornerRadius": 0,
        "curveFrom": "{1, 0.77614237489692062}",
        "curveMode": 2,
        "curveTo": "{1, 0.22385762510307938}",
        "hasCurveFrom": true,
        "hasCurveTo": true,
        "point": "{1, 0.5}"
      },
      {
        "_class": "curvePoint",
        "cornerRadius": 0,
        "curveFrom": "{0.22385762510307936, 1}",
        "curveMode": 4,
        "curveTo": "{0.77614237489692051, 1}",
        "hasCurveFrom": true,
        "hasCurveTo": true,
        "point": "{0.5, 1}"
      }
    ]
  },
  "pointRadiusBehaviour": 0,
  "points": [
    {
      "_class": "curvePoint",
      "cornerRadius": 0,
      "curveFrom": "{0, 0.22385762510307947}",
      "curveMode": 2,
      "curveTo": "{0, 0.77614237489692084}",
      "hasCurveFrom": true,
      "hasCurveTo": true,
      "point": "{0, 0.5}"
    },
    {
      "_class": "curvePoint",
      "cornerRadius": 0,
      "curveFrom": "{0.77614237489692073, 0}",
      "curveMode": 2,
      "curveTo": "{0.22385762510307963, 0}",
      "hasCurveFrom": true,
      "hasCurveTo": true,
      "point": "{0.5, 0}"
    },
    {
      "_class": "curvePoint",
      "cornerRadius": 0,
      "curveFrom": "{1, 0.77614237489692062}",
      "curveMode": 2,
      "curveTo": "{1, 0.22385762510307938}",
      "hasCurveFrom": true,
      "hasCurveTo": true,
      "point": "{1, 0.5}"
    },
    {
      "_class": "curvePoint",
      "cornerRadius": 0,
      "curveFrom": "{0.22385762510307936, 1}",
      "curveMode": 4,
      "curveTo": "{0.77614237489692051, 1}",
      "hasCurveFrom": true,
      "hasCurveTo": true,
      "point": "{0.5, 1}"
    }
  ],
  "resizingConstraint": 63,
  "resizingType": 0,
  "rotation": 0,
  "shouldBreakMaskChain": false
}