{
  "_class": "rectangle",
  "booleanOperation": -1,
  "do_objectID": "A1D533F5-F1A2-4D68-AC9E-FC1A83881C0B",
  "edited": true,
  "exportOptions": {
    "_class": "exportOptions",
    "do_objectID": "85DFAD9E-7A49-479F-9A99-92AF8A704664",
    "exportFormats": [
    ],
    "includedLayerIds": [
    ],
    "layerOptions": 0,
    "shouldTrim": false
  },
  "fixedRadius": 0,
  "frame": {
    "_class": "rect",
    "constrainProportions": false,
    "do_objectID": "B4915F98-19BA-4158-8B76-92686BA2DE38",
    "height": 5,
    "width": 5,
    "x": 0,
    "y": 11.00866699208018
  },
  "hasConvertedToNewRoundCorners": true,
  "isClosed": true,
  "isFlippedHorizontal": false,
  "isFlippedVertical": false,
  "isLocked": false,
  "isVisible": true,
  "layerListExpandedType": 0,
  "name": "Rectangle 295",
  "nameIsFixed": false,
  "path": {
    "_class": "path",
    "isClosed": true,
    "pointRadiusBehaviour": 0,
    "points": [
      {
        "_class": "curvePoint",
        "cornerRadius": 0,
        "curveFrom": "{0, 0}",
        "curveMode": 1,
        "curveTo": "{0, 0}",
        "hasCurveFrom": false,
        "hasCurveTo": false,
        "point": "{0, 0}"
      },
      {
        "_class": "curvePoint",
        "cornerRadius": 0,
        "curveFrom": "{0, 0.80000000000000004}",
        "curveMode": 1,
        "curveTo": "{0, 0.80000000000000004}",
        "hasCurveFrom": false,
        "hasCurveTo": false,
        "point": "{0, 0.80000000000000004}"
      },
      {
        "_class": "curvePoint",
        "cornerRadius": 0,
        "curveFrom": "{0.42416992183076629, 1}",
        "curveMode": 2,
        "curveTo": "{0, 1}",
        "hasCurveFrom": true,
        "hasCurveTo": true,
        "point": "{0.21208496091538315, 1}"
      },
      {
        "_class": "curvePoint",
        "cornerRadius": 0,
        "curveFrom": "{1, 1}",
        "curveMode": 1,
        "curveTo": "{1, 1}",
        "hasCurveFrom": false,
        "hasCurveTo": false,
        "point": "{1, 1}"
      }
    ]
  },
  "pointRadiusBehaviour": 0,
  "points": [
    {
      "_class": "curvePoint",
      "cornerRadius": 0,
      "curveFrom": "{0, 0}",
      "curveMode": 1,
      "curveTo": "{0, 0}",
      "hasCurveFrom": false,
      "hasCurveTo": false,
      "point": "{0, 0}"
    },
    {
      "_class": "curvePoint",
      "cornerRadius": 0,
      "curveFrom": "{0, 0.80000000000000004}",
      "curveMode": 1,
      "curveTo": "{0, 0.80000000000000004}",
      "hasCurveFrom": false,
      "hasCurveTo": false,
      "point": "{0, 0.80000000000000004}"
    },
    {
      "_class": "curvePoint",
      "cornerRadius": 0,
      "curveFrom": "{0.42416992183076629, 1}",
      "curveMode": 2,
      "curveTo": "{0, 1}",
      "hasCurveFrom": true,
      "hasCurveTo": true,
      "point": "{0.21208496091538315, 1}"
    },
    {
      "_class": "curvePoint",
      "cornerRadius": 0,
      "curveFrom": "{1, 1}",
      "curveMode": 1,
      "curveTo": "{1, 1}",
      "hasCurveFrom": false,
      "hasCurveTo": false,
      "point": "{1, 1}"
    }
  ],
  "resizingConstraint": 63,
  "resizingType": 0,
  "rotation": 0,
  "shouldBreakMaskChain": false
}